forwarderd/__init__.py
forwarderd/__main__.py
forwarderd/_daemon.py
forwarderd/_shared.py
forwarderd-13.dist-info/LICENSE
forwarderd-13.dist-info/METADATA
forwarderd-13.dist-info/WHEEL
forwarderd-13.dist-info/top_level.txt
forwarderd-13.dist-info/RECORD
