Metadata-Version: 2.1
Name: forwarderd
Version: 13
Summary: SSH Forward Daemon
Author-email: Elchin Sarkarov <elchin751@gmail.com>
Project-URL: Homepage, https://github.com/elchinchel/forwarderd
Project-URL: Bug Tracker, https://github.com/elchinchel/forwarderd/issues
Classifier: Development Status :: 4 - Beta
Classifier: Programming Language :: Python :: 3
Classifier: License :: OSI Approved :: Apache Software License
Classifier: Operating System :: POSIX
Classifier: Operating System :: Microsoft :: Windows
Requires-Python: >=3.7
License-File: LICENSE
Provides-Extra: daemon
Requires-Dist: paramiko ; extra == 'daemon'
Requires-Dist: sshtunnel ; extra == 'daemon'
Provides-Extra: test
Requires-Dist: pytest ; extra == 'test'
Requires-Dist: pytest-asyncio ; extra == 'test'
Requires-Dist: pytest-dotenv ; extra == 'test'
